{
	"name": "Julius Caesar",
	"format": "play",
	"year": "1599",
	"writingCredits": [
		{
			"entities": [
				{
					"name": "William Shakespeare"
				}
			]
		}
	],
	"characterGroups": [
		{
			"characters": [
				{
					"name": "Julius Caesar"
				},
				{
					"name": "Calphurnia"
				}
			]
		},
		{
			"name": "Conspirators against Caesar",
			"characters": [
				{
					"name": "Marcus Brutus"
				},
				{
					"name": "Caius Cassius"
				},
				{
					"name": "Casca"
				},
				{
					"name": "Decius Brutus"
				},
				{
					"name": "Cinna",
					"differentiator": "Julius Caesar #1"
				},
				{
					"name": "Metellus Cimber"
				},
				{
					"name": "Trebonius"
				},
				{
					"name": "Caius Ligarius"
				}
			]
		},
		{
			"name": "Triumvirs after Caesar's death",
			"characters": [
				{
					"name": "Octavius Caesar"
				},
				{
					"name": "Mark Antony"
				},
				{
					"name": "Lepidus"
				}
			]
		},
		{
			"name": "Roman Senators",
			"characters": [
				{
					"name": "Cicero"
				},
				{
					"name": "Publius",
					"differentiator": "Julius Caesar"
				},
				{
					"name": "Popilius Lena"
				}
			]
		},
		{
			"name": "Tribunes of the People",
			"characters": [
				{
					"name": "Flavius",
					"differentiator": "Julius Caesar"
				},
				{
					"name": "Marullus"
				}
			]
		},
		{
			"name": "Followers of Brutus and Cassius",
			"characters": [
				{
					"name": "Volumnius"
				},
				{
					"name": "Titinius"
				},
				{
					"name": "Young Cato"
				},
				{
					"name": "Messala"
				},
				{
					"name": "Varro"
				},
				{
					"name": "Clitus"
				},
				{
					"name": "Claudius",
					"differentiator": "Julius Caesar"
				},
				{
					"name": "Dardanius"
				},
				{
					"name": "Strato"
				},
				{
					"name": "Lucilius",
					"differentiator": "Julius Caesar"
				},
				{
					"name": "Pindarus"
				}
			]
		},
		{
			"name": "Citizens",
			"characters": [
				{
					"name": "Portia",
					"differentiator": "Julius Caesar"
				},
				{
					"name": "Artemidorus"
				},
				{
					"name": "Cinna",
					"differentiator": "Julius Caesar #2"
				},
				{
					"name": "Lucius",
					"differentiator": "Julius Caesar"
				},
				{
					"name": "Soothsayer",
					"differentiator": "Julius Caesar"
				},
				{
					"name": "Poet",
					"differentiator": "Julius Caesar"
				},
				{
					"name": "Cobbler"
				},
				{
					"name": "Carpenter"
				}
			]
		},
		{
			"characters": [
				{
					"name": "Servant to Julius Caesar"
				},
				{
					"name": "Servant to Mark Antony"
				},
				{
					"name": "Servant to Octavius Caesar"
				},
				{
					"name": "Messenger",
					"differentiator": "Julius Caesar"
				},
				{
					"name": "Senators",
					"differentiator": "Julius Caesar"
				},
				{
					"name": "Soldiers",
					"differentiator": "Julius Caesar"
				},
				{
					"name": "Plebeians",
					"differentiator": "Julius Caesar"
				},
				{
					"name": "Attendants",
					"differentiator": "Julius Caesar"
				}
			]
		}
	]
}
