{
	"name": "Rock 'n' Roll",
	"startDate": "2006-06-03",
	"pressDate": "2006-06-14",
	"endDate": "2006-07-15",
	"material": {
		"name": "Rock 'n' Roll"
	},
	"venue": {
		"name": "Jerwood Theatre Downstairs"
	},
	"producerCredits": [
		{
			"entities": [
				{
					"model": "company",
					"name": "Royal Court Theatre"
				}
			]
		}
	],
	"cast": [
		{
			"name": "Edward Hogg",
			"roles": [
				{
					"name": "The Piper"
				},
				{
					"name": "Policeman 1"
				},
				{
					"name": "Stephen"
				}
			]
		},
		{
			"name": "Alice Eve",
			"roles": [
				{
					"name": "Esme",
					"qualifier": "younger"
				},
				{
					"name": "Alice"
				}
			]
		},
		{
			"name": "Rufus Sewell",
			"roles": [
				{
					"name": "Jan"
				}
			]
		},
		{
			"name": "Brian Cox",
			"roles": [
				{
					"name": "Max"
				}
			]
		},
		{
			"name": "Sinead Cusack",
			"roles": [
				{
					"name": "Eleanor"
				},
				{
					"name": "Esme",
					"qualifier": "older"
				}
			]
		},
		{
			"name": "Miranda Colchester",
			"roles": [
				{
					"name": "Gillian"
				},
				{
					"name": "Magda"
				},
				{
					"name": "Pupil"
				}
			]
		},
		{
			"name": "Anthony Calf",
			"roles": [
				{
					"name": "Interrogator"
				},
				{
					"name": "Nigel"
				}
			]
		},
		{
			"name": "Peter Sullivan",
			"roles": [
				{
					"name": "Ferdinand"
				}
			]
		},
		{
			"name": "Martin Chamberlain",
			"roles": [
				{
					"name": "Milan"
				},
				{
					"name": "Policeman 2"
				},
				{
					"name": "Jaroslav"
				}
			]
		},
		{
			"name": "Nicole Ansari",
			"roles": [
				{
					"name": "Lenka"
				}
			]
		},
		{
			"name": "Lousie Bangay",
			"roles": [
				{
					"name": "Candida"
				}
			]
		}
	],
	"creativeCredits": [
		{
			"name": "Director",
			"entities": [
				{
					"name": "Trevor Nunn"
				}
			]
		},
		{
			"name": "Designer",
			"entities": [
				{
					"name": "Robert Jones"
				}
			]
		},
		{
			"name": "Costume Designer",
			"entities": [
				{
					"name": "Emma Ryott"
				}
			]
		},
		{
			"name": "Lighting Designer",
			"entities": [
				{
					"name": "Howard Harrison"
				}
			]
		},
		{
			"name": "Sound Designer",
			"entities": [
				{
					"name": "Ian Dickinson"
				}
			]
		}
	]
}
