{
	"uuid": "fe508161-1661-4a0e-9cd3-b6fcab7d66df",
	"name": "From Elsewhere: The Message…",
	"startDate": "2012-02-09",
	"pressDate": "2012-02-20",
	"endDate": "2012-04-01",
	"material": {
		"name": "From Elsewhere: The Message…"
	},
	"venue": {
		"name": "Tricycle Theatre"
	},
	"cast": [
		{
			"name": "Rick Warden",
			"roles": [
				{
					"name": "Rudolf Peieris",
					"characterName": "Rudolf"
				}
			]
		},
		{
			"name": "Daniel Rabin",
			"roles": [
				{
					"name": "Otto Frisch",
					"characterName": "Otto"
				}
			]
		},
		{
			"name": "Simon Chandler",
			"roles": [
				{
					"name": "Clerk"
				}
			]
		}
	]
}
